setup.py
txtarantool.py
txtarantool.egg-info/PKG-INFO
txtarantool.egg-info/SOURCES.txt
txtarantool.egg-info/dependency_links.txt
txtarantool.egg-info/requires.txt
txtarantool.egg-info/top_level.txt