Metadata-Version: 1.0
Name: txtarantool
Version: 0.6
Summary: non-blocking tarantool client for python twisted
Home-page: http://github.com/zlobspb/txtarantool
Author: Alexander V. Panfilov
Author-email: zlobspb@gmail.com
License: BSD License
Platform: UNKNOWN
